fortitudo/tech/__init__.py
fortitudo/tech/data/parameters.csv
fortitudo/tech/data/pnl.csv
fortitudo/tech/data/risk_factors.csv
fortitudo/tech/data/time_series.csv
fortitudo/tech/data.py
fortitudo/tech/entropy_pooling.py
fortitudo/tech/functions.py
fortitudo/tech/optimization.py
fortitudo/tech/option_pricing.py
fortitudo/tech/simulation.py
fortitudo_tech-1.2.dist-info/METADATA
fortitudo_tech-1.2.dist-info/WHEEL
fortitudo_tech-1.2.dist-info/LICENSE
fortitudo_tech-1.2.dist-info/RECORD
