Metadata-Version: 2.1
Name: fortitudo-tech
Version: 1.2
Summary: Entropy Pooling views and stress-testing combined with Conditional Value-at-Risk (CVaR) portfolio optimization in Python.
Home-page: https://fortitudo.tech
License: GPL-3.0-or-later
Keywords: CVaR,Efficient Frontier,Entropy Pooling,Quantitative Finance,Portfolio Optimization
Author: Fortitudo Technologies
Author-email: software@fortitudo.tech
Requires-Python: >=3.9,<3.14
Classifier: Intended Audience :: Education
Classifier: Intended Audience :: Financial and Insurance Industry
Classifier: Intended Audience :: Science/Research
Classifier: License :: OSI Approved :: GNU General Public License v3 or later (GPLv3+)
Classifier: Programming Language :: Python :: 3
Classifier: Programming Language :: Python :: 3.9
Classifier: Programming Language :: Python :: 3.10
Classifier: Programming Language :: Python :: 3.11
Classifier: Programming Language :: Python :: 3.10
Classifier: Programming Language :: Python :: 3.11
Classifier: Programming Language :: Python :: 3.12
Classifier: Programming Language :: Python :: 3.13
Classifier: Programming Language :: Python :: 3.9
Classifier: Topic :: Office/Business :: Financial
Classifier: Topic :: Office/Business :: Financial :: Investment
Classifier: Topic :: Scientific/Engineering :: Mathematics
Requires-Dist: cvxopt (>=1.3.0,<2.0.0)
Requires-Dist: matplotlib (>=3.4,<4.0)
Requires-Dist: numpy (>=1.22)
Requires-Dist: pandas (>=1.3.4)
Requires-Dist: scipy (>=1.10,<2.0)
Project-URL: Documentation, https://os.fortitudo.tech
Project-URL: Issues, https://github.com/fortitudo-tech/fortitudo.tech/issues
Project-URL: Repository, https://github.com/fortitudo-tech/fortitudo.tech
